bruma/__init__.py
bruma/py.typed
bruma-0.1.0.dist-info/LICENSE
bruma-0.1.0.dist-info/WHEEL
bruma-0.1.0.dist-info/METADATA
bruma-0.1.0.dist-info/RECORD
